pyf_login/__init__.py
pyf_login/base_model.py
pyf_login/base_serializer.py
pyf_login/jwt_token.py
pyf_login/models.py
pyf_login/my_date_time.py
pyf_login/serializers.py
pyf_login/urls.py
pyf_login/utils.py
pyf_login/views.py
pyf_login-0.24.dist-info/LICENSE
pyf_login-0.24.dist-info/METADATA
pyf_login-0.24.dist-info/WHEEL
pyf_login-0.24.dist-info/top_level.txt
pyf_login-0.24.dist-info/RECORD
