Metadata-Version: 2.1
Name: pyf_login
Version: 0.24
Summary: A reusable Django login package
Home-page: https://kessho.dev/spark-python-core/spark-auth
Author: ycx
Author-email: ycx3030@126.com
Classifier: Development Status :: 3 - Alpha
Classifier: Framework :: Django
Classifier: Intended Audience :: Developers
Classifier: License :: OSI Approved :: MIT License
Classifier: Programming Language :: Python :: 3
Classifier: Programming Language :: Python :: 3.7
Classifier: Programming Language :: Python :: 3.8
Classifier: Programming Language :: Python :: 3.9
Classifier: Programming Language :: Python :: 3.10
Classifier: Programming Language :: Python :: 3.12
License-File: LICENSE
Requires-Dist: djangorestframework
Requires-Dist: PyJWT
